seq_optimizer-0.1.2.dist-info/METADATA
seq_optimizer-0.1.2.dist-info/WHEEL
seq_optimizer-0.1.2.dist-info/RECORD
seq_optimizer-0.1.2.dist-info/top_level.txt
seq_optimizer-0.1.2.dist-info/LICENSE
seq_optimizer/__init__.py
seq_optimizer/_seq_optimizer.cpython-311-x86_64-linux-gnu.so
seq_optimizer/core.py
