Metadata-Version: 2.1
Name: seq_optimizer
Version: 0.1.2
Summary: A Rust-based Python package for sequence optimization
Author: Rungrod Thongjampa
Author-email: rungrodks@hotmail.com
License: MIT License
Project-URL: homepage, https://github.com/rungrodkspeed/seq_optimizer
Project-URL: repository, https://github.com/rungrodkspeed/seq_optimizer
Requires-Python: >=3.10
License-File: LICENSE
